chromedriver_autoupdater
