Metadata-Version: 2.1
Name: chromedriver-autoupdater
Version: 0.6.5
Summary: Automatically install chromedriver that supports the currently installed version of chrome.
Home-page: https://github.com/shawnCaza/python-chromedriver-autoinstaller
Author: Shawn Caza
Author-email: theshawn@gmail.com
License: MIT
Keywords: chromedriver chrome chromium selenium
Classifier: Development Status :: 5 - Production/Stable
Classifier: Topic :: Software Development :: Testing
Classifier: Topic :: System :: Installation/Setup
Classifier: Topic :: Software Development :: Libraries :: Python Modules
Classifier: License :: OSI Approved :: MIT License
Classifier: Programming Language :: Python :: 3
Classifier: Programming Language :: Python :: 3.6
Classifier: Programming Language :: Python :: 3.7
Classifier: Programming Language :: Python :: 3.8
Classifier: Programming Language :: Python :: 3.9
Classifier: Programming Language :: Python :: 3.10
Classifier: Programming Language :: Python :: 3.11
Requires-Python: >=3.6
License-File: LICENSE
